chat.py
cli.py
deepwiki_to_md.py
search_repository.py
deepwiki_to_md-2.0.3.data/data/share/deepwiki_to_md/config.json
deepwiki_to_md-2.0.3.dist-info/licenses/LICENSE
deepwiki_to_md-2.0.3.dist-info/METADATA
deepwiki_to_md-2.0.3.dist-info/WHEEL
deepwiki_to_md-2.0.3.dist-info/entry_points.txt
deepwiki_to_md-2.0.3.dist-info/top_level.txt
deepwiki_to_md-2.0.3.dist-info/RECORD
